pdsys/__init__.py
pdsys/__version__.py
pdsys/example.py
pdsys/ssh.py
pdsys/utils.py
pdsys-0.3.dist-info/METADATA
pdsys-0.3.dist-info/WHEEL
pdsys-0.3.dist-info/top_level.txt
pdsys-0.3.dist-info/RECORD
