Metadata-Version: 2.1
Name: pdsys
Version: 0.3
Summary: Pandas-powered package for systems monitoring
Home-page: https://github.com/abduhbm/pdsys
Author: Abdulelah Bin Mahfoodh
License: MIT
Keywords: system monitoring pandas metrics performance
Platform: UNKNOWN
Classifier: Development Status :: 3 - Alpha
Classifier: License :: OSI Approved :: MIT License
Classifier: Programming Language :: Python
Classifier: Programming Language :: Python :: 3
Classifier: Programming Language :: Python :: 3.7
Classifier: Programming Language :: Python :: 3.8
Classifier: Topic :: Utilities
Classifier: Topic :: Software Development :: Libraries :: Python Modules
Classifier: Topic :: Software Development :: Libraries
Classifier: Topic :: System :: Monitoring
Classifier: Topic :: System :: Systems Administration
Requires-Dist: psutil
Requires-Dist: pandas
